Metadata-Version: 2.1
Name: console-contacts
Version: 1.2.0
Summary: CLI contacts manager
Home-page: UNKNOWN
Author: Kai Harris
License: MIT
Keywords: console cli contacts contact addressbook
Platform: UNKNOWN
Classifier: Development Status :: 4 - Beta
Classifier: Intended Audience :: Developers
Classifier: Topic :: Software Development :: Build Tools
Classifier: License :: OSI Approved :: MIT License
Classifier: Programming Language :: Python :: 3
Classifier: Programming Language :: Python :: 3.4
Classifier: Programming Language :: Python :: 3.5
Classifier: Programming Language :: Python :: 3.6
